django_genericadmin-0.7.0.dist-info/DESCRIPTION.rst
django_genericadmin-0.7.0.dist-info/METADATA
django_genericadmin-0.7.0.dist-info/RECORD
django_genericadmin-0.7.0.dist-info/WHEEL
django_genericadmin-0.7.0.dist-info/metadata.json
django_genericadmin-0.7.0.dist-info/top_level.txt
genericadmin/__init__.py
genericadmin/admin.py
genericadmin/static/genericadmin/js/genericadmin.js
