Metadata-Version: 2.0
Name: django-genericadmin
Version: 0.7.0
Summary: Adds support for generic relations within Django's admin interface.
Home-page: https://github.com/arthanson/django-genericadmin
Author: Weston Nielson, Jan Schrewe, Arthur Hanson
Author-email: wnielson@gmail.com, jschrewe@googlemail.com, worldnomad@gmail.com
License: UNKNOWN
Platform: UNKNOWN
Classifier: Development Status :: 3 - Alpha
Classifier: Environment :: Web Environment
Classifier: Intended Audience :: Developers
Classifier: License :: OSI Approved :: BSD License
Classifier: Operating System :: OS Independent
Classifier: Programming Language :: Python
Classifier: Framework :: Django
